pdk_semver/.gitignore
pdk_semver/__init__.py
pdk_semver/__main__.py
pdk_semver/__version__.py
pdk_semver/scm.py
pdk_semver/scm_common.py
pdk_semver/scm_git.py
pdk_semver/ver.py
pdk_semver-1.3.0.dist-info/entry_points.txt
pdk_semver-1.3.0.dist-info/WHEEL
pdk_semver-1.3.0.dist-info/METADATA
pdk_semver-1.3.0.dist-info/licenses/LICENSE
pdk_semver-1.3.0.dist-info/RECORD
