Metadata-Version: 2.1
Name: pdk-semver
Version: 1.3.0
Summary: Versioning tool
Author-email: Anatoly Asviyan <jon@dot.com>
Classifier: Development Status :: 4 - Beta
Classifier: Environment :: Console
Classifier: Intended Audience :: Developers
Classifier: License :: OSI Approved :: MIT License
Classifier: Operating System :: POSIX
Classifier: Programming Language :: Python :: 3
Classifier: Topic :: Software Development
Requires-Dist: pydevkit<4.0.0,>=3.1.2
Project-URL: Homepage, https://github.com/aanatoly/pdk-semver
Project-URL: Repository, https://github.com/aanatoly/pdk-semver
